pozansky_stock_server/__init__.py
pozansky_stock_server/__main__.py
pozansky_stock_server/asdf.py
pozansky_stock_server/server.py
pozansky_stock_server/stock_analysis_test_20251003_191419.md
pozansky_stock_server/stock_analysis_test_20251003_192925.md
pozansky_stock_server/stock_analysis_test_20251003_194405.md
pozansky_stock_server/stock_analysis_test_20251003_195807.md
pozansky_stock_server/stock_analysis_test_20251003_200014.md
pozansky_stock_server/stock_analysis_test_ERROR.md
pozansky_stock_server/test.py
pozansky_stock-0.1.0.dist-info/METADATA
pozansky_stock-0.1.0.dist-info/WHEEL
pozansky_stock-0.1.0.dist-info/entry_points.txt
pozansky_stock-0.1.0.dist-info/RECORD
