Metadata-Version: 2.4
Name: pozansky_stock
Version: 0.1.0
Summary: Add your description here
Requires-Python: >=3.10
Requires-Dist: build>=1.3.0
Requires-Dist: hatchling>=1.27.0
Requires-Dist: httpx>=0.24.0
Requires-Dist: mcp[cli]>=1.15.0
Requires-Dist: numpy>=1.24.0
Requires-Dist: pandas>=2.0.0
Requires-Dist: psutil>=5.9.0
